taichi/CHANGELOG.md
taichi/__init__.py
taichi/__main__.py
taichi/_funcs.py
taichi/_kernels.py
taichi/_logging.py
taichi/_main.py
taichi/_version_check.py
taichi/experimental.py
taichi/_lib/__init__.py
taichi/_lib/utils.py
taichi/_lib/c_api/include/taichi/taichi.h
taichi/_lib/c_api/include/taichi/taichi_core.h
taichi/_lib/c_api/include/taichi/taichi_cpu.h
taichi/_lib/c_api/include/taichi/taichi_cuda.h
taichi/_lib/c_api/include/taichi/taichi_opengl.h
taichi/_lib/c_api/include/taichi/taichi_platform.h
taichi/_lib/c_api/include/taichi/taichi_unity.h
taichi/_lib/c_api/include/taichi/taichi_vulkan.h
taichi/_lib/c_api/include/taichi/cpp/taichi.hpp
taichi/_lib/c_api/lib/libtaichi_c_api.so
taichi/_lib/c_api/runtime/runtime_cuda.bc
taichi/_lib/c_api/runtime/runtime_x64.bc
taichi/_lib/c_api/runtime/slim_libdevice.10.bc
taichi/_lib/c_api/taichi/lib/cmake/taichi/TaichiConfig.cmake
taichi/_lib/c_api/taichi/lib/cmake/taichi/TaichiConfigVersion.cmake
taichi/_lib/c_api/taichi/lib/cmake/taichi/TaichiTargets.cmake
taichi/_lib/core/taichi_python.cpython-310-x86_64-linux-gnu.so
taichi/_lib/runtime/runtime_cuda.bc
taichi/_lib/runtime/runtime_x64.bc
taichi/_lib/runtime/slim_libdevice.10.bc
taichi/_snode/__init__.py
taichi/_snode/fields_builder.py
taichi/_snode/snode_tree.py
taichi/_ti_module/__init__.py
taichi/_ti_module/cppgen.py
taichi/_ti_module/module.py
taichi/ad/__init__.py
taichi/ad/_ad.py
taichi/algorithms/__init__.py
taichi/algorithms/_algorithms.py
taichi/aot/__init__.py
taichi/aot/_export.py
taichi/aot/module.py
taichi/aot/utils.py
taichi/aot/conventions/__init__.py
taichi/aot/conventions/gfxruntime140/__init__.py
taichi/aot/conventions/gfxruntime140/dr.py
taichi/aot/conventions/gfxruntime140/sr.py
taichi/assets/.git
taichi/assets/Go-Regular.ttf
taichi/assets/static/imgs/ti_gallery.png
taichi/examples/minimal.py
taichi/examples/patterns.py
taichi/examples/algorithm/laplace.py
taichi/examples/algorithm/marching_squares.py
taichi/examples/algorithm/mciso_advanced.py
taichi-1.7.4.dist-info/licenses/LICENSE
taichi-1.7.4.dist-info/METADATA
taichi-1.7.4.dist-info/WHEEL
taichi-1.7.4.dist-info/entry_points.txt
taichi-1.7.4.dist-info/top_level.txt
taichi-1.7.4.dist-info/RECORD
