Metadata-Version: 2.2
Name: taichi
Version: 1.7.4
Summary: The Taichi Programming Language
Home-page: https://github.com/taichi-dev/taichi
Author: Taichi developers
Author-email: yuanmhu@gmail.com
License: Apache Software License (http://www.apache.org/licenses/LICENSE-2.0)
Keywords: graphics,simulation
Classifier: Development Status :: 5 - Production/Stable
Classifier: Topic :: Software Development :: Compilers
Classifier: Topic :: Multimedia :: Graphics
Classifier: Topic :: Games/Entertainment :: Simulation
Classifier: Intended Audience :: Science/Research
Classifier: Intended Audience :: Developers
Classifier: License :: OSI Approved :: Apache Software License
Classifier: Programming Language :: Python :: 3.9
Classifier: Programming Language :: Python :: 3.10
Classifier: Programming Language :: Python :: 3.11
Requires-Python: >=3.9,<4.0
License-File: LICENSE
Requires-Dist: numpy
Requires-Dist: colorama
Requires-Dist: dill
Requires-Dist: rich
Dynamic: author
Dynamic: author-email
Dynamic: classifier
Dynamic: home-page
Dynamic: keywords
Dynamic: license
Dynamic: requires-dist
Dynamic: requires-python
Dynamic: summary
